{
  "projectData": [
    {
      "name": "Todo Crud App in React",
      "image": "./Project-img/crud-app.png",
      "github": "https://github.com/dazzlerabhi30800/todo-crud-with-animation",
      "live": "https://todo-crud-with-animation.vercel.app/"
    },
    {
      "name": "Epic Games Clone",
      "image": "./Project-img/epic-games.png",
      "github": "https://github.com/dazzlerabhi30800/epic-games-store-clone",
      "live": "https://epic-games-store-clone-ashy.vercel.app/"
    },
    {
      "name": "Metflix Movie App",
      "image": "./Project-img/movie-app.png",
      "github": "https://github.com/dazzlerabhi30800/metflix-movie-app",
      "live": "https://metflix-movie-app.vercel.app/"
    },
    {
      "name": "Spotify Music App",
      "image": "./Project-img/music-app.png",
      "github": "https://github.com/dazzlerabhi30800/music-app-ReactJS",
      "live": "https://music-app-react-js.vercel.app/"
    },
    {
      "name": "Netflix Landing Page",
      "image": "./Project-img/netflix-landing-page.png",
      "github": "https://github.com/dazzlerabhi30800/netflix-welcome-page-clone-in-react",
      "live": "https://netflix-welcome-page-clone-in-react.vercel.app/"
    },
    {
      "name": "Rock Paper Scissors Game",
      "image": "./Project-img/rock-paper-scissor.png",
      "github": "https://github.com/dazzlerabhi30800/frontendMentor-Rock-paper-scissors-game-in-Next.js",
      "live": "https://frontend-mentor-rock-paper-scissors-game-in-next-js.vercel.app/"
    }
  ]
}
